rabbitizer.cp312-win_amd64.pyd
rabbitizer/Abi.pyi
rabbitizer/AccessType.pyi
rabbitizer/Config.pyi
rabbitizer/Enum.pyi
rabbitizer/InstrCategory.pyi
rabbitizer/InstrId.pyi
rabbitizer/InstrIdType.pyi
rabbitizer/JrRegData.pyi
rabbitizer/LoPairingInfo.pyi
rabbitizer/OperandType.pyi
rabbitizer/RegCop1N32.pyi
rabbitizer/RegCop1N64.pyi
rabbitizer/RegCop1O32.pyi
rabbitizer/RegGprN32.pyi
rabbitizer/RegGprO32.pyi
rabbitizer/RegistersTracker.pyi
rabbitizer/TrackedRegisterState.pyi
rabbitizer/TrinaryValue.pyi
rabbitizer/Utils.pyi
rabbitizer/__init__.pyi
rabbitizer/py.typed
rabbitizer/rabbitizer.pyi
rabbitizer/rabbitizer_global_config.c
rabbitizer/rabbitizer_macro_utilities.h
rabbitizer/rabbitizer_module.c
rabbitizer/rabbitizer_module.h
rabbitizer/rabbitizer_submodule_Utils.c
rabbitizer/rabbitizer_type_Instruction.c
rabbitizer/rabbitizer_type_JrRegData.c
rabbitizer/rabbitizer_type_LoPairingInfo.c
rabbitizer/rabbitizer_type_RegistersTracker.c
rabbitizer/rabbitizer_type_TrackedRegisterState.c
rabbitizer/enums/enums_utils.c
rabbitizer/enums/enums_utils.h
rabbitizer/enums/rabbitizer_enum_Abi.c
rabbitizer/enums/rabbitizer_enum_AccessType.c
rabbitizer/enums/rabbitizer_enum_InstrCategory.c
rabbitizer/enums/rabbitizer_enum_InstrId.c
rabbitizer/enums/rabbitizer_enum_InstrIdType.c
rabbitizer/enums/rabbitizer_enum_OperandType.c
rabbitizer/enums/rabbitizer_enum_TrinaryValue.c
rabbitizer/enums/rabbitizer_type_Enum.c
rabbitizer/enums/registers/rabbitizer_enum_Cop1N32.c
rabbitizer/enums/registers/rabbitizer_enum_Cop1N64.c
rabbitizer/enums/registers/rabbitizer_enum_Cop1O32.c
rabbitizer/enums/registers/rabbitizer_enum_GprN32.c
rabbitizer/enums/registers/rabbitizer_enum_GprO32.c
rabbitizer-1.14.3.dist-info/licenses/LICENSE
rabbitizer-1.14.3.dist-info/METADATA
rabbitizer-1.14.3.dist-info/WHEEL
rabbitizer-1.14.3.dist-info/top_level.txt
rabbitizer-1.14.3.dist-info/RECORD
