Metadata-Version: 2.4
Name: rabbitizer
Version: 1.14.3
Summary: MIPS instruction decoder
Author-email: Anghelo Carvajal <angheloalf95@gmail.com>
Project-URL: Homepage, https://github.com/Decompollaborate/rabbitizer
Project-URL: Bug Tracker, https://github.com/Decompollaborate/rabbitizer/issues
Requires-Python: >=3.9
License-File: LICENSE
Dynamic: license-file
